tipsa
