Metadata-Version: 1.1
Name: tipsa-api-python
Version: 0.1.5
Summary: Create packages to send using TIPSA API.
Home-page: https://bitbucket.org/abalt/tipsa-api-python
Author: Abalt
Author-email: admin@abalt.org
License: Copyright (c) 2011, Tangent Communications PLC and individual contributors.
